MCQuantLib/__init__.py
MCQuantLib/Engine/__init__.py
MCQuantLib/Engine/engine.py
MCQuantLib/Instrument/__init__.py
MCQuantLib/Instrument/instrument.py
MCQuantLib/Instrument/AsianOption/__init__.py
MCQuantLib/Instrument/AsianOption/asianOption.py
MCQuantLib/Instrument/AsianOption/AveragePriceAsianOption/__init__.py
MCQuantLib/Instrument/AsianOption/AveragePriceAsianOption/averagePriceAsianOption.py
MCQuantLib/Instrument/AsianOption/AverageStrikeAsianOption/__init__.py
MCQuantLib/Instrument/AsianOption/AverageStrikeAsianOption/averageStrikeAsianOption.py
MCQuantLib/Instrument/AutoCallOption/__init__.py
MCQuantLib/Instrument/AutoCallOption/autocallOption.py
MCQuantLib/Instrument/AutoCallOption/SnowBallOption/__init__.py
MCQuantLib/Instrument/AutoCallOption/SnowBallOption/snowBallOption.py
MCQuantLib/Instrument/BarrierOption/__init__.py
MCQuantLib/Instrument/BarrierOption/barrierOption.py
MCQuantLib/Instrument/BarrierOption/DoubleBarrierOption/__init__.py
MCQuantLib/Instrument/BarrierOption/DoubleBarrierOption/doubleBarrierOption.py
MCQuantLib/Instrument/BarrierOption/SingleBarrierOption/__init__.py
MCQuantLib/Instrument/BarrierOption/SingleBarrierOption/singleBarrierOption.py
MCQuantLib/Instrument/BarrierOption/SingleBarrierOption/DownBarrierOption/__init__.py
MCQuantLib/Instrument/BarrierOption/SingleBarrierOption/DownBarrierOption/downBarrierOption.py
MCQuantLib/Instrument/BarrierOption/SingleBarrierOption/UpBarrierOption/__init__.py
MCQuantLib/Instrument/BarrierOption/SingleBarrierOption/UpBarrierOption/upBarrierOption.py
MCQuantLib/Instrument/VanillaOption/__init__.py
MCQuantLib/Instrument/VanillaOption/vanillaOption.py
MCQuantLib/Instrument/VanillaOption/VanillaCallOption/__init__.py
MCQuantLib/Instrument/VanillaOption/VanillaCallOption/vanillaCallOption.py
MCQuantLib/Instrument/VanillaOption/VanillaPutOption/__init__.py
MCQuantLib/Instrument/VanillaOption/VanillaPutOption/vanillaPutOption.py
MCQuantLib/Path/__init__.py
MCQuantLib/Path/path.py
mcquantlib-0.1.26.dist-info/METADATA
mcquantlib-0.1.26.dist-info/WHEEL
mcquantlib-0.1.26.dist-info/top_level.txt
mcquantlib-0.1.26.dist-info/RECORD
