Metadata-Version: 2.4
Name: MCQuantLib
Version: 0.1.26
Summary: MCQuantLib is a QuantLib derivative to perform Monte Carlo pricing of options.
Home-page: https://mcquantlib-doc.readthedocs.io/en/latest/index.html
Author: Syuya_Murakami
Author-email: wxy135@mail.ustc.edu.cn
Project-URL: Bug Tracker, https://github.com/SyuyaMurakami/MCQuantLib
Classifier: Programming Language :: Python :: 3
Classifier: License :: OSI Approved :: MIT License
Classifier: Operating System :: OS Independent
Requires-Python: >=3.8
Requires-Dist: numpy
Requires-Dist: pandas
Requires-Dist: QuantLib
Requires-Dist: joblib
Dynamic: author
Dynamic: author-email
Dynamic: classifier
Dynamic: description
Dynamic: description-content-type
Dynamic: home-page
Dynamic: project-url
Dynamic: requires-dist
Dynamic: requires-python
Dynamic: summary
